__init__.py
data/__init__.py
data/preprocessing.py
features/__init__.py
features/review_features.py
models/__init__.py
models/ensemble.py
womens_clothing_recommender-1.0.1.dist-info/licenses/LICENSE
womens_clothing_recommender-1.0.1.dist-info/METADATA
womens_clothing_recommender-1.0.1.dist-info/WHEEL
womens_clothing_recommender-1.0.1.dist-info/entry_points.txt
womens_clothing_recommender-1.0.1.dist-info/top_level.txt
womens_clothing_recommender-1.0.1.dist-info/RECORD
