Metadata-Version: 2.4
Name: womens-clothing-recommender
Version: 1.0.1
Summary: High-performance clothing recommendation predictor using ensemble ML
Author-email: Celil Vural <celilvural.work@gmail.com>
License: MIT
Project-URL: Homepage, https://github.com/celil-vural/womens-clothing-recommender
Project-URL: Repository, https://github.com/celil-vural/womens-clothing-recommender
Project-URL: Issues, https://github.com/celil-vural/womens-clothing-recommender/issues
Keywords: machine-learning,nlp,e-commerce,recommendation,ensemble
Classifier: Programming Language :: Python :: 3
Classifier: License :: OSI Approved :: MIT License
Classifier: Operating System :: OS Independent
Classifier: Topic :: Scientific/Engineering :: Artificial Intelligence
Classifier: Intended Audience :: Science/Research
Classifier: Intended Audience :: Developers
Requires-Python: >=3.10
License-File: LICENSE
Requires-Dist: pandas==2.3.3
Requires-Dist: numpy==2.2.6
Requires-Dist: scikit-learn==1.7.2
Requires-Dist: matplotlib==3.10.7
Requires-Dist: matplotlib-inline==0.1.3
Requires-Dist: joblib==1.5.2
Requires-Dist: kagglehub==0.3.13
Requires-Dist: tqdm==4.67.1
Requires-Dist: pathspec==0.9.0
Dynamic: license-file
